drevalpy/__init__.py
drevalpy/cli.py
drevalpy/cli_model_testing.py
drevalpy/cli_preprocess_custom.py
drevalpy/cli_run_cv.py
drevalpy/datasets/__init__.py
drevalpy/datasets/curvecurator.py
drevalpy/datasets/dataset.py
drevalpy/datasets/featurizer/create_chemberta_drug_embeddings.py
drevalpy/datasets/featurizer/create_drug_graphs.py
drevalpy/datasets/featurizer/create_molgnet_embeddings.py
drevalpy/datasets/loader.py
drevalpy/datasets/map_tissues.py
drevalpy/datasets/utils.py
drevalpy/evaluation.py
drevalpy/experiment.py
drevalpy/models/DIPK/__init__.py
drevalpy/models/DIPK/attention_utils.py
drevalpy/models/DIPK/data_utils.py
drevalpy/models/DIPK/dipk.py
drevalpy/models/DIPK/gene_expression_encoder.py
drevalpy/models/DIPK/hyperparameters.yaml
drevalpy/models/DIPK/model_utils.py
drevalpy/models/DrugGNN/__init__.py
drevalpy/models/DrugGNN/drug_gnn.py
drevalpy/models/DrugGNN/hyperparameters.yaml
drevalpy/models/MOLIR/__init__.py
drevalpy/models/MOLIR/hyperparameters.yaml
drevalpy/models/MOLIR/molir.py
drevalpy/models/MOLIR/utils.py
drevalpy/models/README.md
drevalpy/models/SRMF/__init__.py
drevalpy/models/SRMF/hyperparameters.yaml
drevalpy/models/SRMF/srmf.py
drevalpy/models/SimpleNeuralNetwork/__init__.py
drevalpy/models/SimpleNeuralNetwork/hyperparameters.yaml
drevalpy/models/SimpleNeuralNetwork/multiomics_neural_network.py
drevalpy/models/SimpleNeuralNetwork/simple_neural_network.py
drevalpy/models/SimpleNeuralNetwork/utils.py
drevalpy/models/SuperFELTR/__init__.py
drevalpy/models/SuperFELTR/hyperparameters.yaml
drevalpy/models/SuperFELTR/superfeltr.py
drevalpy/models/SuperFELTR/utils.py
drevalpy/models/__init__.py
drevalpy/models/baselines/__init__.py
drevalpy/models/baselines/hyperparameters.yaml
drevalpy/models/baselines/multi_omics_random_forest.py
drevalpy/models/baselines/naive_pred.py
drevalpy/models/baselines/singledrug_elastic_net.py
drevalpy/models/baselines/singledrug_random_forest.py
drevalpy/models/baselines/sklearn_models.py
drevalpy-1.4.1.dist-info/METADATA
drevalpy-1.4.1.dist-info/WHEEL
drevalpy-1.4.1.dist-info/entry_points.txt
drevalpy-1.4.1.dist-info/licenses/LICENSE
drevalpy-1.4.1.dist-info/RECORD
