Metadata-Version: 2.4
Name: drevalpy
Version: 1.4.1
Summary: Drug response evaluation of cancer cell line drug response models in a fair setting
License: GPL-3.0
License-File: LICENSE
Author: DrEvalPy development team
Requires-Python: >=3.11,<3.14
Classifier: License :: OSI Approved :: GNU General Public License v3 (GPLv3)
Classifier: Programming Language :: Python :: 3
Classifier: Programming Language :: Python :: 3.11
Classifier: Programming Language :: Python :: 3.12
Classifier: Programming Language :: Python :: 3.13
Provides-Extra: multiprocessing
Requires-Dist: curve-curator
Requires-Dist: flaky
Requires-Dist: importlib-resources
Requires-Dist: matplotlib
Requires-Dist: networkx
Requires-Dist: numpy (>=1.20)
Requires-Dist: pandas
Requires-Dist: plotly
Requires-Dist: poetry (>=2.0.1,<3.0.0)
Requires-Dist: pydantic (>=2.5) ; extra == "multiprocessing"
Requires-Dist: pytorch-lightning (>=2.5)
Requires-Dist: pyyaml
Requires-Dist: ray[tune] ; extra == "multiprocessing"
Requires-Dist: requests
Requires-Dist: scikit-learn (>=1.4)
Requires-Dist: scikit-posthocs
Requires-Dist: scipy
Requires-Dist: starlette (>=0.49.1)
Requires-Dist: toml (>=0.10.2,<0.11.0)
Requires-Dist: torch (>=2.1)
Requires-Dist: torch-geometric
